pyinstaller_plus/__init__.py
pyinstaller_plus/__main__.py
pyinstaller_plus/cli.py
pyinstaller_plus/distromate.py
pyinstaller_plus/bin/distromate.exe
pyinstaller_plus/bin/resource/InnoSetup/Default.isl
pyinstaller_plus/bin/resource/InnoSetup/ISCC.exe
pyinstaller_plus/bin/resource/InnoSetup/ISCmplr.dll
pyinstaller_plus/bin/resource/InnoSetup/ISCmplr.dll.issig
pyinstaller_plus/bin/resource/InnoSetup/Setup.e32
pyinstaller_plus/bin/resource/InnoSetup/Setup.e32.issig
pyinstaller_plus/bin/resource/InnoSetup/SetupLdr.e32
pyinstaller_plus/bin/resource/InnoSetup/SetupLdr.e32.issig
pyinstaller_plus/bin/resource/InnoSetup/isbunzip.dll
pyinstaller_plus/bin/resource/InnoSetup/isbunzip.dll.issig
pyinstaller_plus/bin/resource/InnoSetup/islzma.dll
pyinstaller_plus/bin/resource/InnoSetup/islzma.dll.issig
pyinstaller_plus/bin/resource/InnoSetup/isunzlib.dll
pyinstaller_plus/bin/resource/InnoSetup/isunzlib.dll.issig
pyinstaller_plus/bin/resource/InnoSetup/iszlib.dll
pyinstaller_plus/bin/resource/InnoSetup/iszlib.dll.issig
pyinstaller_plus/bin/resource/InnoSetup/Languages/Arabic.isl
pyinstaller_plus/bin/resource/InnoSetup/Languages/Armenian.isl
pyinstaller_plus/bin/resource/InnoSetup/Languages/BrazilianPortuguese.isl
pyinstaller_plus/bin/resource/InnoSetup/Languages/Bulgarian.isl
pyinstaller_plus/bin/resource/InnoSetup/Languages/Catalan.isl
pyinstaller_plus/bin/resource/InnoSetup/Languages/ChineseSimplified.isl
pyinstaller_plus/bin/resource/InnoSetup/Languages/Corsican.isl
pyinstaller_plus/bin/resource/InnoSetup/Languages/Czech.isl
pyinstaller_plus/bin/resource/InnoSetup/Languages/Danish.isl
pyinstaller_plus/bin/resource/InnoSetup/Languages/Dutch.isl
pyinstaller_plus/bin/resource/InnoSetup/Languages/Finnish.isl
pyinstaller_plus/bin/resource/InnoSetup/Languages/French.isl
pyinstaller_plus/bin/resource/InnoSetup/Languages/German.isl
pyinstaller_plus/bin/resource/InnoSetup/Languages/Hebrew.isl
pyinstaller_plus/bin/resource/InnoSetup/Languages/Hungarian.isl
pyinstaller_plus-0.1.6.dist-info/METADATA
pyinstaller_plus-0.1.6.dist-info/WHEEL
pyinstaller_plus-0.1.6.dist-info/entry_points.txt
pyinstaller_plus-0.1.6.dist-info/top_level.txt
pyinstaller_plus-0.1.6.dist-info/RECORD
