Metadata-Version: 2.4
Name: pyinstaller-plus
Version: 0.1.6
Summary: PyInstaller wrapper that runs DistroMate packaging/publish after build
License-Expression: LicenseRef-Proprietary
Keywords: pyinstaller,distromate,packaging,installer,publish
Classifier: Development Status :: 3 - Alpha
Classifier: Intended Audience :: Developers
Classifier: Operating System :: Microsoft :: Windows
Classifier: Programming Language :: Python :: 3
Classifier: Programming Language :: Python :: 3 :: Only
Classifier: Topic :: Software Development :: Build Tools
Requires-Python: >=3.9
Requires-Dist: pyinstaller
Requires-Dist: tomli; python_version < "3.11"
